cnit/__init__.py
cnit/configs/experiment_config.py
cnit/configs/model_config.py
cnit/physics/__init__.py
cnit/physics/carbon_cycle.py
cnit/physics/carbon_nitrogen_cycle.py
cnit/physics/effects.py
cnit/physics/landuse.py
cnit/physics/nitrogen_cycle.py
cnit/utils/__init__.py
cnit/utils/data_utils.py
cnit/utils/maths.py
cnit/utils/units.py
cnit-2.1.0.dist-info/METADATA
cnit-2.1.0.dist-info/WHEEL
cnit-2.1.0.dist-info/top_level.txt
cnit-2.1.0.dist-info/RECORD
