Metadata-Version: 2.4
Name: cnit
Version: 2.1.0
Summary: CNit: A Coupled Carbon-Nitrogen Cycle Model (Python)
Author-email: Gang Tang <gang.tang.au@gmail.com>, Zebedee Nicholls <zebedee.nicholls@climate-energy-college.org>, Alexander Norton <alex.norton@csiro.au>, Sönke Zaehle <szaehle@bgc-jena.mpg.de>, Malte Meinshausen <malte.meinshausen@unimelb.edu.au>
Maintainer-email: Gang Tang <gang.tang.au@gmail.com>
License: BSD-3-Clause
Project-URL: Homepage, https://github.com/gangtang-au/cnit
Project-URL: Documentation, https://cnit.readthedocs.io
Project-URL: Repository, https://github.com/gangtang-au/cnit
Project-URL: Changelog, https://cnit.readthedocs.io/en/latest/changelog.html
Keywords: cnit,carbon cycle,nitrogen cycle,simple climate model,magicc
Classifier: Development Status :: 4 - Beta
Classifier: License :: OSI Approved :: BSD License
Classifier: Operating System :: OS Independent
Classifier: Intended Audience :: Developers
Classifier: Intended Audience :: Science/Research
Classifier: Intended Audience :: End Users/Desktop
Classifier: Programming Language :: Python
Classifier: Programming Language :: Python :: 3
Classifier: Programming Language :: Python :: 3.9
Classifier: Programming Language :: Python :: 3.10
Classifier: Programming Language :: Python :: 3.11
Classifier: Programming Language :: Python :: 3.12
Classifier: Topic :: Scientific/Engineering
Requires-Python: >=3.9
Requires-Dist: numpy
Requires-Dist: scipy
Requires-Dist: xarray==2023.6.0
Requires-Dist: netCDF4
Requires-Dist: attrs
Requires-Dist: openscm-units>=0.5.0
Requires-Dist: pint>=0.19
Provides-Extra: notebook
Requires-Dist: notebook<7,>=6; extra == "notebook"
Requires-Dist: matplotlib; extra == "notebook"
Provides-Extra: docs
Requires-Dist: sphinx>=1.4; extra == "docs"
Requires-Dist: sphinx-rtd-theme>=1.0; extra == "docs"
Requires-Dist: sphinx-autodoc-typehints>=1.22; extra == "docs"
Requires-Dist: sphinxcontrib-bibtex; extra == "docs"
Provides-Extra: tests
Requires-Dist: pytest; extra == "tests"
Requires-Dist: pytest-regressions[dataframe]; extra == "tests"
